bioio_imageio/__init__.py
bioio_imageio/metadata_utils.py
bioio_imageio/py.typed
bioio_imageio/reader.py
bioio_imageio/reader_metadata.py
bioio_imageio/writers/__init__.py
bioio_imageio/writers/timeseries_writer.py
bioio_imageio/writers/two_d_writer.py
bioio_imageio-1.3.0.dist-info/licenses/LICENSE
bioio_imageio-1.3.0.dist-info/METADATA
bioio_imageio-1.3.0.dist-info/WHEEL
bioio_imageio-1.3.0.dist-info/entry_points.txt
bioio_imageio-1.3.0.dist-info/top_level.txt
bioio_imageio-1.3.0.dist-info/RECORD
