Metadata-Version: 2.4
Name: bioio-imageio
Version: 1.3.0
Summary: A BioIO reader plugin for reading simple image formats using imageio.
Author-email: Sean Meharry <seanm@alleninstitute.org>
License: MIT License
Project-URL: Homepage, https://github.com/bioio-devs/bioio-imageio
Project-URL: Bug Tracker, https://github.com/bioio-devs/bioio-imageio/issues
Project-URL: Documentation, https://bioio-devs.github.io/bioio-imageio
Project-URL: User Support, https://github.com/bioio-devs/bioio-imageio/issues
Classifier: Development Status :: 4 - Beta
Classifier: Natural Language :: English
Classifier: Programming Language :: Python :: 3.10
Classifier: Programming Language :: Python :: 3.11
Classifier: Programming Language :: Python :: 3.12
Classifier: Programming Language :: Python :: 3.13
Requires-Python: >=3.10
License-File: LICENSE
Requires-Dist: bioio-base>=1.4.0
Requires-Dist: dask[array]>=2021.4.1
Requires-Dist: fsspec>=2022.8.0
Requires-Dist: imageio[ffmpeg]>=2.31.0
Requires-Dist: numpy>=1.21.0
Requires-Dist: Pillow>=9.3.0
Requires-Dist: xarray>=2022.6.0
Provides-Extra: lint
Requires-Dist: pre-commit>=2.20.0; extra == "lint"
Provides-Extra: test
Requires-Dist: coverage>=5.1; extra == "test"
Requires-Dist: pytest>=5.4.3; extra == "test"
Requires-Dist: pytest-cov>=2.9.0; extra == "test"
Requires-Dist: pytest-raises>=0.11; extra == "test"
Dynamic: license-file
